MANIFEST.in
README.rst
REAdME.rst
setup.py
alphahome/__init__.py
alphahome/cmdline.py
alphahome/notify.py
alphahome/signal.py
alphahome.egg-info/PKG-INFO
alphahome.egg-info/SOURCES.txt
alphahome.egg-info/dependency_links.txt
alphahome.egg-info/entry_points.txt
alphahome.egg-info/not-zip-safe
alphahome.egg-info/requires.txt
alphahome.egg-info/top_level.txt
alphahome/cmd/__init__.py
alphahome/cmd/command.py
alphahome/response/__init__.py
alphahome/response/response.py
alphahome/templates/__init__.py
alphahome/templates/app/including.tmpl
alphahome/templates/app/models.tmpl
alphahome/templates/app/views.tmpl
alphahome/utils/__init__.py